bitcaster/__init__.py
bitcaster/admin_site.py
bitcaster/apps.py
bitcaster/checks.py
bitcaster/constants.py
bitcaster/exceptions.py
bitcaster/handlers.py
bitcaster/state.py
bitcaster/version.py
bitcaster/LOCALE/ar/LC_MESSAGES/django.mo
bitcaster/LOCALE/ar/LC_MESSAGES/django.po
bitcaster/LOCALE/de/LC_MESSAGES/django.mo
bitcaster/LOCALE/de/LC_MESSAGES/django.po
bitcaster/LOCALE/en/LC_MESSAGES/django.mo
bitcaster/LOCALE/en/LC_MESSAGES/django.po
bitcaster/LOCALE/es/LC_MESSAGES/django.mo
bitcaster/LOCALE/es/LC_MESSAGES/django.po
bitcaster/LOCALE/fr/LC_MESSAGES/django.mo
bitcaster/LOCALE/fr/LC_MESSAGES/django.po
bitcaster/LOCALE/it/LC_MESSAGES/django.mo
bitcaster/LOCALE/it/LC_MESSAGES/django.po
bitcaster/admin/__init__.py
bitcaster/admin/address.py
bitcaster/admin/api_key.py
bitcaster/admin/application.py
bitcaster/admin/assignment.py
bitcaster/admin/base.py
bitcaster/admin/channel.py
bitcaster/admin/distribution.py
bitcaster/admin/event.py
bitcaster/admin/filters.py
bitcaster/admin/group.py
bitcaster/admin/internal.py
bitcaster/admin/media.py
bitcaster/admin/member.py
bitcaster/admin/message.py
bitcaster/admin/mixins.py
bitcaster/admin/monitor.py
bitcaster/admin/notification.py
bitcaster/admin/occurrence.py
bitcaster/admin/organization.py
bitcaster/admin/overrides.py
bitcaster/admin/project.py
bitcaster/admin/register.py
bitcaster/admin/task.py
bitcaster/admin/user.py
bitcaster/admin/user_message.py
bitcaster/admin/userrole.py
bitcaster/agents/__init__.py
bitcaster/agents/base.py
bitcaster/agents/fs.py
bitcaster/agents/ftp.py
bitcaster/api/__init__.py
bitcaster/api/application.py
bitcaster/api/base.py
bitcaster/api/channel.py
bitcaster/api/distribution_list.py
bitcaster/api/event.py
bitcaster/api/org.py
bitcaster/api/permissions.py
bitcaster/api/profile.py
bitcaster/api/project.py
bitcaster/api/serializers.py
bitcaster/api/system.py
bitcaster/api/urls.py
bitcaster/api/user.py
bitcaster/auth/__init__.py
bitcaster/auth/backends.py
bitcaster/auth/constants.py
bitcaster-2.2.dist-info/METADATA
bitcaster-2.2.dist-info/WHEEL
bitcaster-2.2.dist-info/entry_points.txt
bitcaster-2.2.dist-info/licenses/LICENSE.md
bitcaster-2.2.dist-info/RECORD
