Metadata-Version: 2.4
Name: bitcaster
Version: 2.2
Author-email: Bitcaster Team <info@bitcaster.io>
License: OS4D
License-File: LICENSE.md
Classifier: Programming Language :: Python :: 3 :: Only
Classifier: Programming Language :: Python :: 3.13
Requires-Python: ==3.13.*
Requires-Dist: apscheduler>=3.11.2
Requires-Dist: click>=8.3.1
Requires-Dist: colorlog>=6.10.1
Requires-Dist: cron-descriptor>=2.0.6
Requires-Dist: cryptography==45.0.3
Requires-Dist: django-ace>=1.43.3
Requires-Dist: django-admin-extra-buttons>=2.1.1
Requires-Dist: django-adminactions>=2.3
Requires-Dist: django-adminfilters>=2.6
Requires-Dist: django-anymail>=10.3
Requires-Dist: django-concurrency>=2.5
Requires-Dist: django-constance>=3.1
Requires-Dist: django-csp>=3.8
Requires-Dist: django-debug-toolbar>=4.3
Requires-Dist: django-environ>=0.11.2
Requires-Dist: django-filter>=24.2
Requires-Dist: django-flags>=5.0.13
Requires-Dist: django-jsoneditor>=0.2.4
Requires-Dist: django-markdownify>=0.9.5
Requires-Dist: django-migration-linter>=5.2
Requires-Dist: django-online-issues[github]>=0.6
Requires-Dist: django-push-notifications>=3.1
Requires-Dist: django-redis>=5.4
Requires-Dist: django-regex>=0.5
Requires-Dist: django-reversion>=5.0.12
Requires-Dist: django-smart-selects>=1.7.2
Requires-Dist: django-storages[azure,dropbox,google,s3]>=1.14.3
Requires-Dist: django-strategy-field>=3.1
Requires-Dist: django-stubs>=4.2.7
Requires-Dist: django-svelte-jsoneditor>=0.4.2
Requires-Dist: django-taggit>=5.0.1
Requires-Dist: django-tailwind>=4.4.2
Requires-Dist: django-timezone-field>=6.1
Requires-Dist: django-tinymce>=4
Requires-Dist: django-unfold>=0.72
Requires-Dist: django<6,>=5.2.1
Requires-Dist: djangorestframework>=3.15
Requires-Dist: dramatiq>=2
Requires-Dist: drf-extensions>=0.7.1
Requires-Dist: drf-spectacular-sidecar>=2024.4.1
Requires-Dist: drf-spectacular>=0.27.1
Requires-Dist: httpagentparser>=1.9.5
Requires-Dist: jmespath>=1.0.1
Requires-Dist: jsonschema>=4.24
Requires-Dist: mailjet-rest>=1.3.4
Requires-Dist: msgpack>=1.1.2
Requires-Dist: phonenumbers>=8.13.36
Requires-Dist: pillow>=10.2
Requires-Dist: premailer>=3.10
Requires-Dist: psycopg2-binary>=2.9.9
Requires-Dist: py-vapid>=1.9
Requires-Dist: pygments>=2.17.2
Requires-Dist: python-magic>=0.4.27
Requires-Dist: pywebpush>=2
Requires-Dist: qrcode>=7.4.2
Requires-Dist: requests>=2.31
Requires-Dist: sentry-sdk>=1.43
Requires-Dist: setuptools>=75.3
Requires-Dist: slack-notifications>=0.2.2
Requires-Dist: slack-sdk>=3.27.1
Requires-Dist: social-auth-app-django>=5.6
Requires-Dist: social-auth-core>=4.5.3
Requires-Dist: twilio>=9.0.4
Requires-Dist: user-agents>=2.2
